jupyterlab_notebookbuttons/__init__.py
jupyterlab_notebookbuttons/_version.py
jupyterlab_notebookbuttons/labextension/build_log.json
jupyterlab_notebookbuttons/labextension/package.json
jupyterlab_notebookbuttons/labextension/schemas/jupyterlab_notebookbuttons/package.json.orig
jupyterlab_notebookbuttons/labextension/schemas/jupyterlab_notebookbuttons/plugin.json
jupyterlab_notebookbuttons/labextension/static/lib_index_js.0f01e274506f54ecc1fd.js
jupyterlab_notebookbuttons/labextension/static/lib_index_js.0f01e274506f54ecc1fd.js.map
jupyterlab_notebookbuttons/labextension/static/remoteEntry.a563cca07df28ba84ca7.js
jupyterlab_notebookbuttons/labextension/static/remoteEntry.a563cca07df28ba84ca7.js.map
jupyterlab_notebookbuttons/labextension/static/style.js
jupyterlab_notebookbuttons/labextension/static/style_index_js.c3c6531d65966acc8459.js
jupyterlab_notebookbuttons/labextension/static/style_index_js.c3c6531d65966acc8459.js.map
jupyterlab_notebookbuttons/labextension/static/vendors-node_modules_css-loader_dist_runtime_api_js-node_modules_css-loader_dist_runtime_cssW-926fd9.b6abbb4ee87fddd4df59.js
jupyterlab_notebookbuttons/labextension/static/vendors-node_modules_css-loader_dist_runtime_api_js-node_modules_css-loader_dist_runtime_cssW-926fd9.b6abbb4ee87fddd4df59.js.map
jupyterlab_notebookbuttons-0.1.0.data/data/share/jupyter/labextensions/jupyterlab_notebookbuttons/build_log.json
jupyterlab_notebookbuttons-0.1.0.data/data/share/jupyter/labextensions/jupyterlab_notebookbuttons/install.json
jupyterlab_notebookbuttons-0.1.0.data/data/share/jupyter/labextensions/jupyterlab_notebookbuttons/package.json
jupyterlab_notebookbuttons-0.1.0.data/data/share/jupyter/labextensions/jupyterlab_notebookbuttons/schemas/jupyterlab_notebookbuttons/package.json.orig
jupyterlab_notebookbuttons-0.1.0.data/data/share/jupyter/labextensions/jupyterlab_notebookbuttons/schemas/jupyterlab_notebookbuttons/plugin.json
jupyterlab_notebookbuttons-0.1.0.dist-info/LICENSE
jupyterlab_notebookbuttons-0.1.0.dist-info/METADATA
jupyterlab_notebookbuttons-0.1.0.dist-info/WHEEL
jupyterlab_notebookbuttons-0.1.0.dist-info/top_level.txt
jupyterlab_notebookbuttons-0.1.0.dist-info/RECORD
